icdcrawl/__init__.py
icdcrawl/_api.py
icdcrawl/_crawl.py
icdcrawl/_format_utils.py
icdcrawl/_crawler/__init__.py
icdcrawl/_crawler/abstract.py
icdcrawl/_crawler/icd10data_com.py
icdcrawl/_crawler/icd9data_com.py
icdcrawl/_crawler/icdsearch_idv_tw.py
icdcrawl/tests/__init__.py
icdcrawl/tests/test_api.py
icdcrawl-0.0.0.dist-info/LICENSE.txt
icdcrawl-0.0.0.dist-info/METADATA
icdcrawl-0.0.0.dist-info/WHEEL
icdcrawl-0.0.0.dist-info/top_level.txt
icdcrawl-0.0.0.dist-info/RECORD
