Metadata-Version: 2.1
Name: icdcrawl
Version: 0.0.0
Summary: ICD code crawler
Home-page: https://github.com/sunrimii/icdcrawl
Author: sunrimii
Author-email: sunrimii@gmail.com
License: UNKNOWN
Keywords: ICD-10,ICD-9,icd10data,icd9data,crawler
Platform: UNKNOWN
Requires-Python: >=3.10, <4
License-File: LICENSE.txt
